pystackt/__init__.py
pystackt/exploration/__init__.py
pystackt/exploration/graph/__init__.py
pystackt/exploration/graph/dash_app/__init__.py
pystackt/exploration/graph/dash_app/callbacks.py
pystackt/exploration/graph/dash_app/colormaps.py
pystackt/exploration/graph/dash_app/layout.py
pystackt/exploration/graph/dash_app/sql_statements.py
pystackt/exploration/graph/dash_app/stylesheets.py
pystackt/exploration/graph/data_prep/__init__.py
pystackt/exploration/graph/data_prep/sql_statements.py
pystackt/exploration/stat_views/__init__.py
pystackt/exploration/stat_views/sql_statements.py
pystackt/exporters/__init__.py
pystackt/exporters/ocel2/__init__.py
pystackt/exporters/ocel2/map_data.py
pystackt/exporters/ocel2/output_data.py
pystackt/exporters/promg/__init__.py
pystackt/exporters/promg/map_data.py
pystackt/exporters/promg/output_data.py
pystackt/extractors/__init__.py
pystackt/extractors/github/__init__.py
pystackt/extractors/github/class_definitions.py
pystackt/extractors/github/get_data.py
pystackt/extractors/github/initiate_types.py
pystackt/extractors/github/map_data.py
pystackt/extractors/github/output_data.py
pystackt/utils/__init__.py
pystackt-0.1.0.dist-info/licenses/LICENSE
pystackt-0.1.0.dist-info/METADATA
pystackt-0.1.0.dist-info/WHEEL
pystackt-0.1.0.dist-info/top_level.txt
pystackt-0.1.0.dist-info/RECORD
