Metadata-Version: 2.4
Name: pystackt
Version: 0.1.0
Summary: Data preparation for object-centric process mining.
Author-email: Lien Bosmans <lienbosmans@live.com>
License:                                  Apache License
Project-URL: Homepage, https://github.com/LienBosmans/pystackt
Project-URL: Issues, https://github.com/LienBosmans/pystackt/issues
Classifier: Programming Language :: Python :: 3
Classifier: Operating System :: OS Independent
Classifier: License :: OSI Approved :: Apache Software License
Requires-Python: >=3.12
License-File: LICENSE
Requires-Dist: pyarrow
Requires-Dist: polars
Requires-Dist: duckdb>=1.1.0
Requires-Dist: PyGithub
Requires-Dist: dash
Requires-Dist: dash_bootstrap_components
Requires-Dist: dash_cytoscape
Requires-Dist: matplotlib
Dynamic: license-file
